certman/__init__.py
certman/__main__.py
certman/enums.py
certman/main.py
certman/p12.py
certman-0.2.0.dist-info/METADATA
certman-0.2.0.dist-info/WHEEL
certman-0.2.0.dist-info/entry_points.txt
certman-0.2.0.dist-info/RECORD
