Metadata-Version: 2.1
Name: certman
Version: 0.2.0
Summary: Manage keys and certificates using p12 files
Author: Sernin van de Krol
Author-email: serninpc@paneidos.net
Requires-Python: >=3.12,<4.0
Classifier: Programming Language :: Python :: 3
Classifier: Programming Language :: Python :: 3.12
Requires-Dist: cryptography (>=41.0.7,<42.0.0)
Requires-Dist: typer[all] (>=0.9.0,<0.10.0)
